optimized_memory_mcp_server/__init__.py
optimized_memory_mcp_server/__main__.py
optimized_memory_mcp_server/exceptions.py
optimized_memory_mcp_server/interfaces.py
optimized_memory_mcp_server/knowledge_graph_manager.py
optimized_memory_mcp_server/main.py
optimized_memory_mcp_server/optimized_sqlite_manager.py
optimized_memory_mcp_server/api/server.py
optimized_memory_mcp_server/api/tools.py
optimized_memory_mcp_server/core/__init__.py
optimized_memory_mcp_server/core/sanitization/__init__.py
optimized_memory_mcp_server/core/sanitization/base.py
optimized_memory_mcp_server/core/sanitization/strategies.py
optimized_memory_mcp_server/core/sanitization/validators.py
optimized_memory_mcp_server/operations/entity_ops.py
optimized_memory_mcp_server/storage/__init__.py
optimized_memory_mcp_server/storage/base.py
optimized_memory_mcp_server/storage/sqlite/__init__.py
optimized_memory_mcp_server/storage/sqlite/connection.py
optimized_memory_mcp_server/storage/sqlite/manager.py
optimized_memory_mcp_server/storage/sqlite/optimized_manager.py
optimized_memory_mcp_server/storage/sqlite/schema.py
optimized_memory_mcp_server/storage/sqlite/operations/__init__.py
optimized_memory_mcp_server/storage/sqlite/operations/entity_ops.py
optimized_memory_mcp_server/storage/sqlite/operations/relation_ops.py
optimized_memory_mcp_server/storage/sqlite/operations/search_ops.py
optimized_memory_mcp_server/storage/sqlite/utils/__init__.py
optimized_memory_mcp_server/storage/sqlite/utils/sanitization.py
optimized_memory_mcp_server/storage/sqlite/utils/validation.py
optimized_memory_mcp_server/tests/test_memory_server.py
optimized_memory_mcp_server/tests/core/sanitization/test_strategies.py
optimized_memory_mcp_server/utils/sanitization.py
optimized_memory_mcp_server/utils/validation.py
mseep_optimized_memory_mcp_server-0.1.4.dist-info/METADATA
mseep_optimized_memory_mcp_server-0.1.4.dist-info/WHEEL
mseep_optimized_memory_mcp_server-0.1.4.dist-info/entry_points.txt
mseep_optimized_memory_mcp_server-0.1.4.dist-info/licenses/LICENSE
mseep_optimized_memory_mcp_server-0.1.4.dist-info/RECORD
